prog2onnx/__init__.py
prog2onnx/_register_converters.py
prog2onnx/_supported_operators.py
prog2onnx/convert.py
prog2onnx/common/__init__.py
prog2onnx/common/operator_converters/__init__.py
prog2onnx/common/operator_converters/dict_wrapper.py
prog2onnx/common/operator_converters/proglearn.py
prog2onnx/common/parsers/__init__.py
prog2onnx/common/parsers/_proglearn.py
prog2onnx/common/shape_calculators/__init__.py
prog2onnx/common/shape_calculators/dict_wrapper.py
prog2onnx/common/shape_calculators/proglearn.py
prog2onnx/utils/__init__.py
prog2onnx/utils/_constants.py
prog2onnx/utils/_dict_wrapper.py
prog2onnx/utils/helpers/__init__.py
prog2onnx/utils/helpers/dict_utils.py
prog2onnx/utils/helpers/exceptions.py
prog2onnx-0.0.1.dist-info/METADATA
prog2onnx-0.0.1.dist-info/WHEEL
prog2onnx-0.0.1.dist-info/top_level.txt
prog2onnx-0.0.1.dist-info/RECORD
