Metadata-Version: 2.1
Name: prog2onnx
Version: 0.0.1
Summary: Convert Progressive Learning models to ONNX
Home-page: https://github.com/certh-knowledge-project/proglearn-onnx
Author: CERTH-ITI
Author-email: certh-knowledge-project@iti.gr
License: Apache License v2.0
Classifier: Development Status :: 4 - Beta
Classifier: Environment :: Console
Classifier: Intended Audience :: Developers
Classifier: Operating System :: MacOS :: MacOS X
Classifier: Operating System :: Microsoft :: Windows
Classifier: Programming Language :: Python
Classifier: Programming Language :: Python :: 3.8
Classifier: Programming Language :: Python :: 3.9
Classifier: Programming Language :: Python :: 3.10
Classifier: Programming Language :: Python :: 3.11
Classifier: License :: OSI Approved :: Apache Software License
Requires-Dist: proglearn >=0.0.7
Requires-Dist: skl2onnx >=1.14.1
